pykube/__init__.py
pykube/__main__.py
pykube/config.py
pykube/console.py
pykube/exceptions.py
pykube/http.py
pykube/mixins.py
pykube/objects.py
pykube/query.py
pykube/utils.py
pykube_ng-22.9.0.dist-info/LICENSE
pykube_ng-22.9.0.dist-info/WHEEL
pykube_ng-22.9.0.dist-info/METADATA
pykube_ng-22.9.0.dist-info/RECORD
