Metadata-Version: 2.1
Name: pykube-ng
Version: 22.9.0
Summary: Python client library for Kubernetes
Home-page: https://codeberg.org/hjacobs/pykube-ng
License: Apache
Author: Eldarion, Inc.
Author-email: development@eldarion.com
Requires-Python: >=3.8,<4
Classifier: Development Status :: 5 - Production/Stable
Classifier: Environment :: Web Environment
Classifier: Intended Audience :: Developers
Classifier: License :: OSI Approved :: Apache Software License
Classifier: License :: Other/Proprietary License
Classifier: Operating System :: OS Independent
Classifier: Programming Language :: Python
Classifier: Programming Language :: Python :: 3
Classifier: Programming Language :: Python :: 3.8
Classifier: Programming Language :: Python :: 3.9
Classifier: Programming Language :: Python :: 3.10
Classifier: Programming Language :: Python :: 3 :: Only
Classifier: Programming Language :: Python :: 3.10
Classifier: Programming Language :: Python :: 3.6
Classifier: Programming Language :: Python :: 3.7
Classifier: Programming Language :: Python :: 3.8
Classifier: Programming Language :: Python :: 3.9
Provides-Extra: gcp
Provides-Extra: oidc
Requires-Dist: google-auth; extra == "gcp"
Requires-Dist: jsonpath-ng; extra == "gcp"
Requires-Dist: pyyaml
Requires-Dist: requests (>=2.12)
Requires-Dist: requests-oauthlib (>=1.3.0,<2.0.0); extra == "oidc"
Requires-Dist: urllib3 (>=1.26.9)
